{
  "id": 2430,
  "amount": "49.00",
  "amount_refunded": "0.00",
  "installments": 1,
  "description": "Adopta un Bosque - Ciclo: 12",
  "currency": "USD",
  "ip": null,
  "country": null,
  "country_code": null,
  "device": null,
  "type": "card",
  "state": "done",
  "fraud_score": 0,
  "payment_code": null,
  "payment_service": null,
  "expiration_date": null,
  "created_at": "2022-07-01T06:00:06.000000Z",
  "metadata": {
    "ext_user": null,
    "ext_item": null,
    "ext_order": null,
    "ext_ref": null
  },
  "subscriber": null,
  "payment_name": "Visa",
  "badge": "<span class=\"badge badge-success mr-1\">Correcto</span>",
  "icon": "<i class=\"fas fa-check-circle text-success mr-1\" title=\"Correcto\"></i>",
  "created_at_human": "01/07/2022 01:00",
  "business": {
    "shortname": "fundacionlaesperanza",
    "publicname": "Fundación La Esperanza",
    "country_code": "PE",
    "email": "fundacion@laesperanza.com",
    "link": "https://fundacionlaesperanza.tukuy.xyz",
    "country": "Perú"
  },
  "card": {
    "number": "411111******1111",
    "brand": "Visa",
    "type": "credito",
    "category": "Clásica",
    "issuer": "BBVA",
    "country": "PERU",
    "country_code": "PE",
    "type_name": "cr&eacute;dito",
    "logo": "https://tukuy.xyz/fronted/img/icons/cards/Visa.png",
    "brand_name": "Visa"
  },
  "customer": {
    "dni": "10101001",
    "firstname": "Pedrito",
    "lastname": "Huamachuco",
    "email": "todo@gmail.com",
    "phone": "+51 954 781 256",
    "country_code": "PE",
    "timezone": "America/Lima",
    "valid": 1,
    "birthday": null,
    "gender": "unisex",
    "country": "Perú"
  },
  "product": null,
  "subscription": {
    "id": 61,
    "active": true,
    "sofar": 14,
    "fee": 0,
    "next_billing": "2022-10-01T05:00:00.000000Z",
    "cancelled": false,
    "created_at": "2021-07-31T16:13:00.000000Z",
    "next_billing_human": "01/10/2022",
    "created_at_human": "31/07/2021 11:13",
    "tukuy_engine": 1,
    "badge": "<span class=\"badge badge-success mr-1\">ON</span>",
    "plan": {
      "name": "Adopta un Bosque",
      "description": null,
      "fields": null,
      "amount": "49.00",
      "currency": "USD",
      "interval": "meses",
      "interval_count": 1,
      "limit": null,
      "sku": "BOSQUE",
      "trial_days": null,
      "fee": 0,
      "setup_fee": "0.00",
      "fee_as_offer": 0,
      "created_at": "2021-04-29T02:07:18.000000Z"
    }
  }
}

---

{
    "id": 2604,
    "cantidad": "49,00",
    "cantidad_reembolsada": "0.00",
    "cuotas": 0,
    "description": "Adopta un Bosque - Ciclo: 13",
    "moneda": "USD",
    "ip": nulo,
    "país": nulo,
    "código_de_país": nulo,
    "dispositivo": nulo,
    "tipo": "tarjeta",
    "estado": "hecho",
    "puntuación de fraude": 0,
    "código_de_pago": nulo,
    "servicio_de_pago": nulo,
    "fecha_de_vencimiento": nulo,
    "creado_en": "2025-03-23T09:30:04.000000Z",
    "metadatos": {
      "ext_user": nulo,
      "ext_item": nulo,
      "ext_order": nulo,
      "ext_ref": nulo
    },
    "suscriptor": nulo,
    "nombre_de_pago": "Visa",
    "insignia": "<span class=\"insignia insignia-éxito mr-1\">Correcto</span>",
    "icono": "<i class=\"fas fa-check-circle text-success mr-1\" title=\"Correcto\"></i>",
    "creado_en_humano": "23/03/2025 04:30",
    "negocio": {
      "shortname": "fundacionlaesperanza",
      "publicname": "Fundación La Esperanza",
      "código_de_país": "PE",
      "correo electrónico": "fundacion@laesperanza.com",
      "enlace": "https://fundacionlaesperanza.tukuy.xyz",
      "país": "Perú"
    },
    "tarjeta": {
      "número": "41111111****1111",
      "marca": "Visa",
      "tipo": "Débito",
      "categoría": nulo,
      "emisor": "JPMORGAN CHASE BANK, NA",
      "país": "PERÚ",
      "código_de_país": "PE",
      "type_name": "débito",
      "logotipo": "https://tukuy.xyz/fronted/img/icons/cards/Visa.png",
      "marca_nombre": "Visa"
    },
    "cliente": {
      "dni": "45678743",
      "nombre": "Andy",
      "apellido": "Loyola",
      "correo electrónico": "aloyola@gmail.com",
      "teléfono": "+51 968 523 589",
      "código_de_país": "PE",
      "zona horaria": "América/Lima",
      "válido": 1,
      "cumpleaños": nulo,
      "género": "unisex",
      "país": "Perú"
    },
    "producto": nulo,
    "suscripción": {
      "id": 77,
      "activo": verdadero,
      "hasta ahora": 14,
      "tarifa": 0,
      "próxima_facturación": "2025-05-23T05:00:00.000000Z",
      "cancelado": falso,
      "creado_en": "2024-03-24T02:21:17.000000Z",
      "next_billing_human": "23/05/2025",
      "creado_en_humano": "23/03/2024 21:21",
      "motor tukuy": 1,
      "insignia": "<span class=\"insignia insignia-éxito mr-1\">ACTIVADO</span>",
      "plan": {
        "nombre": "Adopta un Bosque",
        "descripción": nulo,
        "campos": nulo,
        "cantidad": "49,00",
        "moneda": "USD",
        "intervalo": "meses",
        "intervalo_de_recuento": 1,
        "límite": nulo,
        "sku": "BOSQUE",
        "días_de_prueba": nulo,
        "tarifa": 0,
        "tarifa de instalación": "0.00",
        "tarifa_como_oferta": 0,
        "creado_en": "2021-04-29T02:07:18.000000Z"
      }
    }
  }